chatwatch/__init__.py
chatwatch/client.py
chatwatch/errors.py
chatwatch/eventhandlers.py
chatwatch/http.py
chatwatch/messageresponse.py
chatwatch/ratelimiters.py
chatwatch/settings.py
chatwatch/statistics.py
chatwatch.py-0.1.0.dist-info/LICENSE
chatwatch.py-0.1.0.dist-info/METADATA
chatwatch.py-0.1.0.dist-info/WHEEL
chatwatch.py-0.1.0.dist-info/top_level.txt
chatwatch.py-0.1.0.dist-info/RECORD
