Metadata-Version: 2.1
Name: chatwatch.py
Version: 0.1.0
Summary: ChatWatch library
Home-page: https://github.com/TAG-Epic/chatwatch.py
Author: Epic
Author-email: admin@itzepic.net
License: GNU GPLv3
Platform: UNKNOWN
